fsutil/__init__.py
fsutil/archives.py
fsutil/args.py
fsutil/checks.py
fsutil/converters.py
fsutil/deps.py
fsutil/info.py
fsutil/io.py
fsutil/metadata.py
fsutil/operations.py
fsutil/paths.py
fsutil/perms.py
fsutil/py.typed
fsutil/types.py
python_fsutil-0.16.0.dist-info/licenses/LICENSE.txt
python_fsutil-0.16.0.dist-info/METADATA
python_fsutil-0.16.0.dist-info/WHEEL
python_fsutil-0.16.0.dist-info/top_level.txt
python_fsutil-0.16.0.dist-info/RECORD
