Metadata-Version: 2.4
Name: python-fsutil
Version: 0.16.0
Summary: high-level file-system operations for lazy devs.
Author-email: Fabio Caccamo <fabio.caccamo@gmail.com>
Maintainer-email: Fabio Caccamo <fabio.caccamo@gmail.com>
License: MIT License
Project-URL: Homepage, https://github.com/fabiocaccamo/python-fsutil
Project-URL: Download, https://github.com/fabiocaccamo/python-fsutil/releases
Project-URL: Documentation, https://github.com/fabiocaccamo/python-fsutil#readme
Project-URL: Issues, https://github.com/fabiocaccamo/python-fsutil/issues
Project-URL: Funding, https://github.com/sponsors/fabiocaccamo/
Project-URL: Twitter, https://twitter.com/fabiocaccamo
Keywords: python,file,system,util,utils,utility,utilities,dir,directory,path,fs,os,shutil,glob
Classifier: Development Status :: 5 - Production/Stable
Classifier: Environment :: MacOS X
Classifier: Environment :: Web Environment
Classifier: Intended Audience :: Developers
Classifier: Intended Audience :: System Administrators
Classifier: License :: OSI Approved :: MIT License
Classifier: Natural Language :: English
Classifier: Operating System :: OS Independent
Classifier: Programming Language :: Python :: 3
Classifier: Programming Language :: Python :: 3.10
Classifier: Programming Language :: Python :: 3.11
Classifier: Programming Language :: Python :: 3.12
Classifier: Programming Language :: Python :: 3.13
Classifier: Programming Language :: Python :: 3.14
Classifier: Programming Language :: Python :: Implementation :: PyPy
Classifier: Topic :: Desktop Environment :: File Managers
Classifier: Topic :: Software Development :: Build Tools
Classifier: Topic :: Software Development :: Libraries :: Python Modules
Classifier: Topic :: System :: Filesystems
Classifier: Topic :: Utilities
License-File: LICENSE.txt
Dynamic: license-file
